hello/counter.sv
module counter (
    input  logic clk,
    input  logic rst_n,
    output logic [3:0] count
);

    always_ff @(posedge clk) begin
        if (!rst_n)
            count <= 4'd0;
        else
            count <= count + 4'd1;
    end

endmodule

hello/tb_counter.sv
`timescale 1ns/1ps

module tb_counter;

    logic clk;
    logic rst_n;
    logic [3:0] count;

    // Instantiate DUT
    counter dut (
        .clk   (clk),
        .rst_n (rst_n),
        .count (count)
    );

    // Clock: 10 ns period
    always #5 clk = ~clk;

    initial begin
        // Initialize
        clk   = 0;
        rst_n = 0;

        // Dump waveforms
        $dumpfile("counter.vcd");
        $dumpvars(0, tb_counter);

        // Hold reset for 2 cycles
        #20;
        rst_n = 1;

        // Run for 20 cycles
        #200;

        $finish;
    end

endmodule

hello/counter.vcd
$date
	Thu Dec 18 22:08:01 2025
$end
$version
	Icarus Verilog
$end
$timescale
	1ps
$end
$scope module tb_counter $end
$var wire 4 ! count [3:0] $end
$var reg 1 " clk $end
$var reg 1 # rst_n $end
$scope module dut $end
$var wire 1 " clk $end
$var wire 1 # rst_n $end
$var reg 4 $ count [3:0] $end
$upscope $end
$upscope $end
$enddefinitions $end
$comment Show the parameter values. $end
$dumpall
$end
#0
$dumpvars
bx $
0#
0"
bx !
$end
#5000
b0 !
b0 $
1"
#10000
0"
#15000
1"
#20000
0"
1#
#25000
b1 !
b1 $
1"
#30000
0"
#35000
b10 !
b10 $
1"
#40000
0"
#45000
b11 !
b11 $
1"
#50000
0"
#55000
b100 !
b100 $
1"
#60000
0"
#65000
b101 !
b101 $
1"
#70000
0"
#75000
b110 !
b110 $
1"
#80000
0"
#85000
b111 !
b111 $
1"
#90000
0"
#95000
b1000 !
b1000 $
1"
#100000
0"
#105000
b1001 !
b1001 $
1"
#110000
0"
#115000
b1010 !
b1010 $
1"
#120000
0"
#125000
b1011 !
b1011 $
1"
#130000
0"
#135000
b1100 !
b1100 $
1"
#140000
0"
#145000
b1101 !
b1101 $
1"
#150000
0"
#155000
b1110 !
b1110 $
1"
#160000
0"
#165000
b1111 !
b1111 $
1"
#170000
0"
#175000
b0 !
b0 $
1"
#180000
0"
#185000
b1 !
b1 $
1"
#190000
0"
#195000
b10 !
b10 $
1"
#200000
0"
#205000
b11 !
b11 $
1"
#210000
0"
#215000
b100 !
b100 $
1"
