thumb1/core/tiny_mem_model.sv
// -----------------------------------------------------------------------------
// tiny_mem_model.sv
//
// Unified single-ported memory model (iverilog-friendly)
//
// IMPORTANT: Synchronous read (1-cycle latency), synchronous write.
// This models real FPGA block RAM behavior for synthesis compatibility.
// -----------------------------------------------------------------------------
module tiny_mem_model #(
  parameter int WORDS = 4096,
  parameter string INIT_HEX = ""
)(
  input  wire        clk,
  input  wire        rst_n,

  input  wire        mem_valid,
  input  wire        mem_we,
  input  wire [31:0] mem_addr,
  input  wire [31:0] mem_wdata,
  input  wire [3:0]  mem_wstrb,
  output reg         mem_ready,
  output reg  [31:0] mem_rdata
);

  reg [31:0] mem [0:WORDS-1];

  wire [31:0] word_index = mem_addr >> 2;

  // Track if we were reading last cycle for 1-cycle read latency
  reg was_reading;

  // Synchronous read/write with proper handshake
  always @(posedge clk or negedge rst_n) begin
    if (!rst_n) begin
      mem_rdata <= 32'd0;
      mem_ready <= 1'b0;
      was_reading <= 1'b0;
    end else begin
      if (mem_valid && mem_we) begin
        // Writes complete immediately (same cycle)
        mem_ready <= 1'b1;
        was_reading <= 1'b0;
      end else if (mem_valid && !mem_we) begin
        // Reads take 1 cycle: latch data now, signal ready next cycle
        mem_rdata <= mem[word_index];
        mem_ready <= was_reading;  // Ready on 2nd consecutive cycle
        was_reading <= 1'b1;
      end else begin
        mem_ready <= 1'b0;
        was_reading <= 1'b0;
      end
    end
  end

  // Zero-fill then load program
  integer i;
  initial begin
    for (i = 0; i < WORDS; i = i + 1)
      mem[i] = 32'd0;

    if (INIT_HEX != "") begin
      $readmemh(INIT_HEX, mem);
    end
  end

  // Synchronous write with byte strobes
  always @(posedge clk) begin
    if (mem_valid && mem_we) begin
      if (mem_wstrb[0]) mem[word_index][ 7: 0] <= mem_wdata[ 7: 0];
      if (mem_wstrb[1]) mem[word_index][15: 8] <= mem_wdata[15: 8];
      if (mem_wstrb[2]) mem[word_index][23:16] <= mem_wdata[23:16];
      if (mem_wstrb[3]) mem[word_index][31:24] <= mem_wdata[31:24];
    end
  end

endmodule

thumb1/core/tiny_thumb_core.sv
// -----------------------------------------------------------------------------
// tiny_thumb_core.sv  (iverilog-friendly, fixed instruction fetch)
//
// Minimal multi-cycle Thumb-1–like core for subset:
//  - MOVS/CMP/ADDS/SUBS (imm8)
//  - LSL/LSR (imm5) [imm5==0 => no shift, C unchanged by default]
//  - STR/LDR word [Rn + (imm5<<2)]
//  - LDR literal [Align(PC,4) + (imm8<<2)]
//  - B, B<cond> (EQ/NE/MI/PL)
// Optional ALU-reg subset: AND/EOR/ORR/CMP
//
// Unified memory interface (valid/ready).
//
// Key fix vs earlier version:
//   - Correct halfword selection in S_WAITI by using a stable fetch_addr (blocking)
//     rather than mem_addr (which updates after the clock edge with <=).
// -----------------------------------------------------------------------------
module tiny_thumb_core #(
  parameter ENABLE_ALU_REG_GROUP = 1,
  parameter STRICT_THUMB_SHIFT32 = 0
)(
  input  wire        clk,
  input  wire        rst_n,

  output reg         mem_valid,
  output reg         mem_we,
  output reg  [31:0] mem_addr,
  output reg  [31:0] mem_wdata,
  output reg  [3:0]  mem_wstrb,
  input  wire        mem_ready,
  input  wire [31:0] mem_rdata
);

  // ----------------------------
  // Architectural state
  // ----------------------------
  reg [31:0] R [0:15];
  reg [31:0] PC;
  reg [15:0] IR;

  reg N, Z, C, V;

  // ----------------------------
  // State machine encoding (no enums)
  // ----------------------------
  localparam S_RESET  = 4'd0;
  localparam S_FETCH  = 4'd1;
  localparam S_WAITI  = 4'd2;
  localparam S_DECODE = 4'd3;
  localparam S_EXEC   = 4'd4;
  localparam S_MEM    = 4'd5;
  localparam S_WAITM  = 4'd6;
  localparam S_TRAP   = 4'd8;

  reg [3:0] st;

  // Decoded op encoding
  localparam OP_NONE    = 4'd0;
  localparam OP_MOV_IMM = 4'd1;
  localparam OP_CMP_IMM = 4'd2;
  localparam OP_ADD_IMM = 4'd3;
  localparam OP_SUB_IMM = 4'd4;
  localparam OP_LSL_IMM = 4'd5;
  localparam OP_LSR_IMM = 4'd6;
  localparam OP_STR_IMM = 4'd7;
  localparam OP_LDR_IMM = 4'd8;
  localparam OP_LDR_LIT = 4'd9;
  localparam OP_B       = 4'd10;
  localparam OP_BCOND   = 4'd11;
  localparam OP_ALU_REG = 4'd12;

  reg [3:0] op;

  // Latched fields
  reg [2:0] d_rd, d_rn, d_rm, d_rt;
  reg [7:0] d_imm8;
  reg [4:0] d_imm5;
  reg [10:0] d_imm11;
  reg [3:0] d_cond4;
  reg [3:0] d_aluop;

  // Temporaries
  reg [31:0] eff_addr;
  reg [31:0] load_data;

  // Stable fetch address for correct halfword selection
  reg [31:0] fetch_addr;

  integer i;

  // ----------------------------
  // Helper functions (iverilog-friendly)
  // ----------------------------
  function [31:0] align4;
    input [31:0] x;
    begin
      align4 = {x[31:2], 2'b00};
    end
  endfunction

  // Sign-extend using shifts (no variable part-select)
  function [31:0] sext_shift;
    input [31:0] x;
    input integer bits;
    reg signed [31:0] sx;
    begin
      sx = x <<< (32-bits);
      sext_shift = sx >>> (32-bits);
    end
  endfunction

  function cond_ok;
    input [3:0] cond;
    begin
      case (cond)
        4'h0: cond_ok = (Z == 1'b1); // EQ
        4'h1: cond_ok = (Z == 1'b0); // NE
        4'h4: cond_ok = (N == 1'b1); // MI
        4'h5: cond_ok = (N == 1'b0); // PL
        default: cond_ok = 1'b0;
      endcase
    end
  endfunction

  // ----------------------------
  // Instruction classify (combinational wires)
  // ----------------------------
  wire [15:0] insn = IR;

  wire is_bcond   = ((insn & 16'hF000) == 16'hD000) && (insn[11:8] != 4'hF);
  wire is_b       = ((insn & 16'hF800) == 16'hE000);
  wire is_ldr_lit = ((insn & 16'hF800) == 16'h4800);
  wire is_ldr_imm = ((insn & 16'hF800) == 16'h6800);
  wire is_str_imm = ((insn & 16'hF800) == 16'h6000);

  wire is_mov_imm = ((insn & 16'hF800) == 16'h2000);
  wire is_cmp_imm = ((insn & 16'hF800) == 16'h2800);
  wire is_add_imm = ((insn & 16'hF800) == 16'h3000);
  wire is_sub_imm = ((insn & 16'hF800) == 16'h3800);

  wire is_lsl_imm = ((insn & 16'hF800) == 16'h0000);
  wire is_lsr_imm = ((insn & 16'hF800) == 16'h0800);

  wire is_alu_reg = ((insn & 16'hFC00) == 16'h4000);

  // ----------------------------
  // Main FSM
  // ----------------------------
  always @(posedge clk or negedge rst_n) begin
    if (!rst_n) begin
      st <= S_RESET;
      op <= OP_NONE;

      PC <= 32'd0;
      IR <= 16'd0;

      N <= 1'b0; Z <= 1'b0; C <= 1'b0; V <= 1'b0;

      mem_valid <= 1'b0;
      mem_we    <= 1'b0;
      mem_addr  <= 32'd0;
      mem_wdata <= 32'd0;
      mem_wstrb <= 4'd0;

      eff_addr  <= 32'd0;
      load_data <= 32'd0;
      fetch_addr <= 32'd0;

      for (i = 0; i < 16; i = i + 1)
        R[i] <= 32'd0;

    end else begin
      // Default bus outputs each cycle
      mem_valid <= 1'b0;
      mem_we    <= 1'b0;
      mem_addr  <= 32'd0;
      mem_wdata <= 32'd0;
      mem_wstrb <= 4'd0;

      case (st)

        S_RESET: begin
          st <= S_FETCH;
        end

        // ------------------------
        // FETCH: request instruction word at PC (byte address)
        // ------------------------
        S_FETCH: begin
          mem_valid <= 1'b1;
          mem_we    <= 1'b0;
          mem_addr  <= PC;

          // Thumb increments by 2 per instruction
          PC <= PC + 32'd2;

          st <= S_WAITI;
        end

        // ------------------------
        // WAITI: latch IR once memory responds
        // Fixed: use stable fetch_addr for halfword selection.
        // ------------------------
        S_WAITI: begin
          // Blocking assignment intentionally: use within this cycle
          fetch_addr = (PC - 32'd2);

          mem_valid <= 1'b1;
          mem_we    <= 1'b0;
          mem_addr  <= fetch_addr;

          if (mem_ready) begin
            if (fetch_addr[1] == 1'b0)
              IR <= mem_rdata[15:0];
            else
              IR <= mem_rdata[31:16];

            st <= S_DECODE;
          end
        end

        // ------------------------
        // DECODE: decide op + latch fields
        // ------------------------
        S_DECODE: begin
          op <= OP_NONE;

          if (is_bcond) begin
            if (insn[11:8]==4'h0 || insn[11:8]==4'h1 || insn[11:8]==4'h4 || insn[11:8]==4'h5) begin
              op <= OP_BCOND;
              d_cond4 <= insn[11:8];
              d_imm8  <= insn[7:0];
              st <= S_EXEC;
            end else begin
              st <= S_TRAP;
            end

          end else if (is_b) begin
            op <= OP_B;
            d_imm11 <= insn[10:0];
            st <= S_EXEC;

          end else if (is_ldr_lit) begin
            op <= OP_LDR_LIT;
            d_rt   <= insn[10:8];
            d_imm8 <= insn[7:0];
            st <= S_EXEC;

          end else if (is_ldr_imm) begin
            op <= OP_LDR_IMM;
            d_imm5 <= insn[10:6];
            d_rn   <= insn[5:3];
            d_rt   <= insn[2:0];
            st <= S_EXEC;

          end else if (is_str_imm) begin
            op <= OP_STR_IMM;
            d_imm5 <= insn[10:6];
            d_rn   <= insn[5:3];
            d_rt   <= insn[2:0];
            st <= S_EXEC;

          end else if (is_mov_imm) begin
            op <= OP_MOV_IMM;
            d_rd   <= insn[10:8];
            d_imm8 <= insn[7:0];
            st <= S_EXEC;

          end else if (is_cmp_imm) begin
            op <= OP_CMP_IMM;
            d_rd   <= insn[10:8];
            d_imm8 <= insn[7:0];
            st <= S_EXEC;

          end else if (is_add_imm) begin
            op <= OP_ADD_IMM;
            d_rd   <= insn[10:8];
            d_imm8 <= insn[7:0];
            st <= S_EXEC;

          end else if (is_sub_imm) begin
            op <= OP_SUB_IMM;
            d_rd   <= insn[10:8];
            d_imm8 <= insn[7:0];
            st <= S_EXEC;

          end else if (is_lsl_imm) begin
            op <= OP_LSL_IMM;
            d_imm5 <= insn[10:6];
            d_rm   <= insn[5:3];
            d_rd   <= insn[2:0];
            st <= S_EXEC;

          end else if (is_lsr_imm) begin
            op <= OP_LSR_IMM;
            d_imm5 <= insn[10:6];
            d_rm   <= insn[5:3];
            d_rd   <= insn[2:0];
            st <= S_EXEC;

          end else if (ENABLE_ALU_REG_GROUP && is_alu_reg) begin
            if (insn[9:6]==4'h0 || insn[9:6]==4'h1 || insn[9:6]==4'hC || insn[9:6]==4'hA) begin
              op <= OP_ALU_REG;
              d_aluop <= insn[9:6];
              d_rm    <= insn[5:3];
              d_rd    <= insn[2:0];
              st <= S_EXEC;
            end else begin
              st <= S_TRAP;
            end

          end else begin
            st <= S_TRAP;
          end
        end

        // ------------------------
        // EXEC: compute results / flags / addresses
        // ------------------------
        S_EXEC: begin
          reg [31:0] A, B, RES;
          reg [32:0] WIDE;
          reg [31:0] off;

          A = 32'd0; B = 32'd0; RES = 32'd0; WIDE = 33'd0; off = 32'd0;

          case (op)

            OP_MOV_IMM: begin
              RES = {24'd0, d_imm8};
              R[{1'b0,d_rd}] <= RES;
              N <= RES[31];
              Z <= (RES == 32'd0);
              st <= S_FETCH;
            end

            OP_CMP_IMM: begin
              A = R[{1'b0,d_rd}];
              B = {24'd0, d_imm8};
              RES = A - B;
              N <= RES[31];
              Z <= (RES == 32'd0);
              C <= (A >= B);
              V <= ((A[31]^B[31]) & (A[31]^RES[31]));
              st <= S_FETCH;
            end

            OP_ADD_IMM: begin
              A = R[{1'b0,d_rd}];
              B = {24'd0, d_imm8};
              RES = A + B;
              WIDE = {1'b0,A} + {1'b0,B};
              R[{1'b0,d_rd}] <= RES;
              N <= RES[31];
              Z <= (RES == 32'd0);
              C <= WIDE[32];
              V <= ((~(A[31]^B[31])) & (A[31]^RES[31]));
              st <= S_FETCH;
            end

            OP_SUB_IMM: begin
              A = R[{1'b0,d_rd}];
              B = {24'd0, d_imm8};
              RES = A - B;
              R[{1'b0,d_rd}] <= RES;
              N <= RES[31];
              Z <= (RES == 32'd0);
              C <= (A >= B);
              V <= ((A[31]^B[31]) & (A[31]^RES[31]));
              st <= S_FETCH;
            end

            OP_LSL_IMM: begin
              A = R[{1'b0,d_rm}];
              if (d_imm5 == 5'd0) begin
                RES = A;
              end else begin
                RES = A << d_imm5;
                C <= A[32 - d_imm5];
              end
              R[{1'b0,d_rd}] <= RES;
              N <= RES[31];
              Z <= (RES == 32'd0);
              st <= S_FETCH;
            end

            OP_LSR_IMM: begin
              A = R[{1'b0,d_rm}];
              if (d_imm5 == 5'd0) begin
                if (STRICT_THUMB_SHIFT32) begin
                  RES = 32'd0;
                  C <= A[31];
                end else begin
                  RES = A;
                end
              end else begin
                RES = A >> d_imm5;
                C <= A[d_imm5-1];
              end
              R[{1'b0,d_rd}] <= RES;
              N <= RES[31];
              Z <= (RES == 32'd0);
              st <= S_FETCH;
            end

            OP_STR_IMM: begin
              eff_addr <= R[{1'b0,d_rn}] + ({27'd0,d_imm5} << 2);
              st <= S_MEM;
            end

            OP_LDR_IMM: begin
              eff_addr <= R[{1'b0,d_rn}] + ({27'd0,d_imm5} << 2);
              st <= S_MEM;
            end

            OP_LDR_LIT: begin
              eff_addr <= align4(PC) + ({24'd0,d_imm8} << 2);
              st <= S_MEM;
            end

            OP_B: begin
              off = sext_shift({20'd0, d_imm11, 1'b0}, 12);
              PC <= PC + off;
              st <= S_FETCH;
            end

            OP_BCOND: begin
              off = sext_shift({23'd0, d_imm8, 1'b0}, 9);
              if (cond_ok(d_cond4))
                PC <= PC + off;
              st <= S_FETCH;
            end

            OP_ALU_REG: begin
              A = R[{1'b0,d_rd}];
              B = R[{1'b0,d_rm}];

              case (d_aluop)
                4'h0: begin // AND
                  RES = A & B;
                  R[{1'b0,d_rd}] <= RES;
                  N <= RES[31]; Z <= (RES==32'd0);
                  st <= S_FETCH;
                end
                4'h1: begin // EOR
                  RES = A ^ B;
                  R[{1'b0,d_rd}] <= RES;
                  N <= RES[31]; Z <= (RES==32'd0);
                  st <= S_FETCH;
                end
                4'hC: begin // ORR
                  RES = A | B;
                  R[{1'b0,d_rd}] <= RES;
                  N <= RES[31]; Z <= (RES==32'd0);
                  st <= S_FETCH;
                end
                4'hA: begin // CMP
                  RES = A - B;
                  N <= RES[31];
                  Z <= (RES == 32'd0);
                  C <= (A >= B);
                  V <= ((A[31]^B[31]) & (A[31]^RES[31]));
                  st <= S_FETCH;
                end
                default: st <= S_TRAP;
              endcase
            end

            default: st <= S_TRAP;
          endcase
        end

        // ------------------------
        // MEM: issue memory op
        // ------------------------
        S_MEM: begin
          mem_valid <= 1'b1;
          mem_addr  <= eff_addr;

          if (op == OP_STR_IMM) begin
            mem_we    <= 1'b1;
            mem_wdata <= R[{1'b0,d_rt}];
            mem_wstrb <= 4'b1111;
          end else begin
            mem_we    <= 1'b0;
            mem_wstrb <= 4'b0000;
          end

          st <= S_WAITM;
        end

        // ------------------------
        // WAITM: wait for memory response; commit load
        // ------------------------
        S_WAITM: begin
          mem_valid <= 1'b1;
          mem_addr  <= eff_addr;

          if (op == OP_STR_IMM) begin
            mem_we    <= 1'b1;
            mem_wdata <= R[{1'b0,d_rt}];
            mem_wstrb <= 4'b1111;
          end else begin
            mem_we    <= 1'b0;
            mem_wstrb <= 4'b0000;
          end

          if (mem_ready) begin
            if (op == OP_LDR_IMM || op == OP_LDR_LIT) begin
              load_data <= mem_rdata;
              R[{1'b0,d_rt}] <= mem_rdata;
            end
            st <= S_FETCH;
          end
        end

        S_TRAP: begin
          st <= S_TRAP;
        end

        default: st <= S_TRAP;
      endcase

      // Mirror PC into R15 for debug visibility
      R[15] <= PC;
    end
  end

endmodule

thumb1/tb.sv
// -----------------------------------------------------------------------------
// tb.sv
//
// Self-checking testbench for tiny_thumb_core + tiny_mem_model.
//
// Expects your current prog.hex to write the value 10 (0x0000000A)
// to memory address 0x00000100, which corresponds to word index 64.
//
// If you change prog.hex to a different test, update EXPECTED_SIG below.
// -----------------------------------------------------------------------------
module tb;

  // 100 MHz-ish clock
  reg clk = 1'b0;
  always #5 clk = ~clk;

  reg rst_n = 1'b0;

  // Memory bus
  wire        mem_valid;
  wire        mem_we;
  wire [31:0] mem_addr;
  wire [31:0] mem_wdata;
  wire [3:0]  mem_wstrb;
  wire        mem_ready;
  wire [31:0] mem_rdata;

  // Signature configuration
  localparam integer SIG_ADDR       = 32'h0000_0100;
  localparam integer SIG_WORD_INDEX = (SIG_ADDR >> 2); // 0x100 >> 2 = 64
  localparam [31:0]  EXPECTED_SIG   = 32'd10;          // current prog.hex writes 10

  // DUT
  tiny_thumb_core dut (
    .clk       (clk),
    .rst_n     (rst_n),
    .mem_valid (mem_valid),
    .mem_we    (mem_we),
    .mem_addr  (mem_addr),
    .mem_wdata (mem_wdata),
    .mem_wstrb (mem_wstrb),
    .mem_ready (mem_ready),
    .mem_rdata (mem_rdata)
  );

  // Memory (unified)
  tiny_mem_model #(
    .WORDS(4096),
    .INIT_HEX("prog.hex")
  ) mem (
    .clk       (clk),
    .rst_n     (rst_n),
    .mem_valid (mem_valid),
    .mem_we    (mem_we),
    .mem_addr  (mem_addr),
    .mem_wdata (mem_wdata),
    .mem_wstrb (mem_wstrb),
    .mem_ready (mem_ready),
    .mem_rdata (mem_rdata)
  );

  // VCD
  initial begin
    $dumpfile("dump.vcd");
    $dumpvars(0, tb);
  end

  // Reset + run + check
  initial begin
    // Hold reset for a few cycles
    rst_n = 1'b0;
    repeat (5) @(posedge clk);
    rst_n = 1'b1;

    // Run long enough for the program to execute and write the signature.
    // Increase this if you add loops or more instructions.
    repeat (600) @(posedge clk);

    // Self-check the signature.
    if (mem.mem[SIG_WORD_INDEX] !== EXPECTED_SIG) begin
      $display("FAIL: mem[%0d] (addr %h) = %h, expected %h",
               SIG_WORD_INDEX, SIG_ADDR, mem.mem[SIG_WORD_INDEX], EXPECTED_SIG);
      $fatal(1);
    end else begin
      $display("PASS: mem[%0d] (addr %h) = %h",
               SIG_WORD_INDEX, SIG_ADDR, mem.mem[SIG_WORD_INDEX]);
    end

    $finish;
  end

endmodule

thumb1/dump.vcd
$date
	Wed Dec 24 10:35:21 2025
$end
$version
	Icarus Verilog
$end
$timescale
	1s
$end
$scope module tb $end
$var wire 4 ! mem_wstrb [3:0] $end
$var wire 1 " mem_we $end
$var wire 32 # mem_wdata [31:0] $end
$var wire 1 $ mem_valid $end
$var wire 1 % mem_ready $end
$var wire 32 & mem_rdata [31:0] $end
$var wire 32 ' mem_addr [31:0] $end
$var parameter 32 ( EXPECTED_SIG $end
$var parameter 32 ) SIG_ADDR $end
$var parameter 32 * SIG_WORD_INDEX $end
$var reg 1 + clk $end
$var reg 1 , rst_n $end
$scope module dut $end
$var wire 1 + clk $end
$var wire 16 - insn [15:0] $end
$var wire 1 . is_bcond $end
$var wire 1 , rst_n $end
$var wire 1 % mem_ready $end
$var wire 32 / mem_rdata [31:0] $end
$var wire 1 0 is_sub_imm $end
$var wire 1 1 is_str_imm $end
$var wire 1 2 is_mov_imm $end
$var wire 1 3 is_lsr_imm $end
$var wire 1 4 is_lsl_imm $end
$var wire 1 5 is_ldr_lit $end
$var wire 1 6 is_ldr_imm $end
$var wire 1 7 is_cmp_imm $end
$var wire 1 8 is_b $end
$var wire 1 9 is_alu_reg $end
$var wire 1 : is_add_imm $end
$var parameter 32 ; ENABLE_ALU_REG_GROUP $end
$var parameter 4 < OP_ADD_IMM $end
$var parameter 4 = OP_ALU_REG $end
$var parameter 4 > OP_B $end
$var parameter 4 ? OP_BCOND $end
$var parameter 4 @ OP_CMP_IMM $end
$var parameter 4 A OP_LDR_IMM $end
$var parameter 4 B OP_LDR_LIT $end
$var parameter 4 C OP_LSL_IMM $end
$var parameter 4 D OP_LSR_IMM $end
$var parameter 4 E OP_MOV_IMM $end
$var parameter 4 F OP_NONE $end
$var parameter 4 G OP_STR_IMM $end
$var parameter 4 H OP_SUB_IMM $end
$var parameter 32 I STRICT_THUMB_SHIFT32 $end
$var parameter 4 J S_DECODE $end
$var parameter 4 K S_EXEC $end
$var parameter 4 L S_FETCH $end
$var parameter 4 M S_MEM $end
$var parameter 4 N S_RESET $end
$var parameter 4 O S_TRAP $end
$var parameter 4 P S_WAITI $end
$var parameter 4 Q S_WAITM $end
$var reg 1 R C $end
$var reg 16 S IR [15:0] $end
$var reg 1 T N $end
$var reg 32 U PC [31:0] $end
$var reg 1 V V $end
$var reg 1 W Z $end
$var reg 4 X d_aluop [3:0] $end
$var reg 4 Y d_cond4 [3:0] $end
$var reg 11 Z d_imm11 [10:0] $end
$var reg 5 [ d_imm5 [4:0] $end
$var reg 8 \ d_imm8 [7:0] $end
$var reg 3 ] d_rd [2:0] $end
$var reg 3 ^ d_rm [2:0] $end
$var reg 3 _ d_rn [2:0] $end
$var reg 3 ` d_rt [2:0] $end
$var reg 32 a eff_addr [31:0] $end
$var reg 32 b fetch_addr [31:0] $end
$var reg 32 c load_data [31:0] $end
$var reg 32 d mem_addr [31:0] $end
$var reg 1 $ mem_valid $end
$var reg 32 e mem_wdata [31:0] $end
$var reg 1 " mem_we $end
$var reg 4 f mem_wstrb [3:0] $end
$var reg 4 g op [3:0] $end
$var reg 4 h st [3:0] $end
$var integer 32 i i [31:0] $end
$scope function align4 $end
$var reg 32 j x [31:0] $end
$upscope $end
$scope function cond_ok $end
$var reg 4 k cond [3:0] $end
$upscope $end
$scope function sext_shift $end
$var reg 32 l sx [31:0] $end
$var reg 32 m x [31:0] $end
$var integer 32 n bits [31:0] $end
$upscope $end
$scope begin $unm_blk_33 $end
$var reg 32 o A [31:0] $end
$var reg 32 p B [31:0] $end
$var reg 32 q RES [31:0] $end
$var reg 33 r WIDE [32:0] $end
$var reg 32 s off [31:0] $end
$upscope $end
$upscope $end
$scope module mem $end
$var wire 1 + clk $end
$var wire 32 t mem_addr [31:0] $end
$var wire 1 $ mem_valid $end
$var wire 32 u mem_wdata [31:0] $end
$var wire 1 " mem_we $end
$var wire 4 v mem_wstrb [3:0] $end
$var wire 1 , rst_n $end
$var wire 32 w word_index [31:0] $end
$var parameter 64 x INIT_HEX $end
$var parameter 32 y WORDS $end
$var reg 32 z mem_rdata [31:0] $end
$var reg 1 % mem_ready $end
$var reg 1 { was_reading $end
$var integer 32 | i [31:0] $end
$upscope $end
$upscope $end
$enddefinitions $end
$comment Show the parameter values. $end
$dumpall
b100000000000 y
b111000001110010011011110110011100101110011010000110010101111000 x
b110 Q
b10 P
b1000 O
b0 N
b101 M
b1 L
b100 K
b11 J
b0 I
b100 H
b111 G
b0 F
b1 E
b110 D
b101 C
b1001 B
b1000 A
b10 @
b1011 ?
b1010 >
b1100 =
b11 <
b1 ;
b1000000 *
b100000000 )
b10100001 (
$end
#0
$dumpvars
b100000000000 |
x{
bx z
b0xxxxxxxxxxxxxxxxxxxxxxxxxxxxxx w
bx v
bx u
bx t
bx s
bx r
bx q
bx p
bx o
bx n
bx m
bx l
bx k
bx j
bx i
bx h
bx g
bx f
bx e
bx d
bx c
bx b
bx a
bx `
bx _
bx ^
bx ]
bx \
bx [
bx Z
bx Y
bx X
xW
xV
bx U
xT
bx S
xR
x:
x9
x8
x7
x6
x5
x4
x3
x2
x1
x0
bx /
x.
bx -
0,
0+
bx '
bx &
x%
x$
bx #
x"
bx !
$end
#5
0.
b0 w
09
03
14
00
0:
07
02
01
06
05
08
b0 b
b0 c
b0 a
b0 !
b0 f
b0 v
b0 #
b0 e
b0 u
b0 '
b0 d
b0 t
0"
0$
0V
0R
0W
0T
b0 -
b0 S
b0 U
b0 g
b0 h
0{
0%
b0 &
b0 /
b0 z
b10000 i
1+
#10
0+
#15
b10000 i
1+
#20
0+
#25
b10000 i
1+
#30
0+
#35
b10000 i
1+
#40
0+
#45
b1 h
1,
1+
#50
0+
#55
b10 h
b10 U
1$
1+
#60
0+
#65
1$
1{
b111000000000010010000000000011 &
b111000000000010010000000000011 /
b111000000000010010000000000011 z
1+
#70
0+
#75
1%
1$
1+
#80
0+
#85
04
12
b11 h
b10000000000011 -
b10000000000011 S
1$
1+
#90
0+
#95
b100 h
b11 \
b0 ]
b1 g
0$
1+
#100
0+
#105
b1 h
0{
0%
b0 s
b0 r
b11 q
b0 p
b0 o
1+
#110
0+
#115
b10 h
b100 U
b10 '
b10 d
b10 t
1$
1+
#120
0+
#125
b10 '
b10 d
b10 t
1$
1{
b10 b
1+
#130
0+
#135
1%
b10 '
b10 d
b10 t
1$
1+
#140
0+
#145
10
02
b11 h
b11100000000001 -
b11100000000001 S
b10 '
b10 d
b10 t
1$
1+
#150
0+
#155
b100 h
b1 \
b100 g
b0 '
b0 d
b0 t
0$
1+
#160
0+
#165
b1 h
1R
0{
0%
b1 p
b11 o
b10 q
1+
#170
0+
#175
b1 w
b10 h
b110 U
b100 '
b100 d
b100 t
1$
1+
#180
0+
#185
b100 '
b100 d
b100 t
1$
1{
b11010001111111010010100000000000 &
b11010001111111010010100000000000 /
b11010001111111010010100000000000 z
b100 b
1+
#190
0+
#195
1%
b100 '
b100 d
b100 t
1$
1+
#200
0+
#205
00
17
b11 h
b10100000000000 -
b10100000000000 S
b100 '
b100 d
b100 t
1$
1+
#210
0+
#215
b0 w
b100 h
b0 \
b10 g
b0 '
b0 d
b0 t
0$
1+
#220
0+
#225
b1 h
0{
0%
b10 q
b0 p
b10 o
1+
#230
0+
#235
b1 w
b10 h
b1000 U
b110 '
b110 d
b110 t
1$
1+
#240
0+
#245
b110 '
b110 d
b110 t
1$
1{
b110 b
1+
#250
0+
#255
1%
b110 '
b110 d
b110 t
1$
1+
#260
0+
#265
1.
07
b11 h
b1101000111111101 -
b1101000111111101 S
b110 '
b110 d
b110 t
1$
1+
#270
0+
#275
b0 w
b100 h
b11111101 \
b1 Y
b1011 g
b0 '
b0 d
b0 t
0$
1+
#280
0+
#285
b1 h
b10 U
0{
0%
b1 k
b11111111111111111111111111111010 s
b11111101000000000000000000000000 l
b111111010 m
b1001 n
b0 q
b0 o
1+
#290
0+
#295
b10 h
b100 U
b10 '
b10 d
b10 t
1$
1+
#300
0+
#305
b10 '
b10 d
b10 t
1$
1{
b111000000000010010000000000011 &
b111000000000010010000000000011 /
b111000000000010010000000000011 z
b10 b
1+
#310
0+
#315
1%
b10 '
b10 d
b10 t
1$
1+
#320
0+
#325
0.
10
b11 h
b11100000000001 -
b11100000000001 S
b10 '
b10 d
b10 t
1$
1+
#330
0+
#335
b100 h
b1 \
b100 g
b0 '
b0 d
b0 t
0$
1+
#340
0+
#345
b1 h
0{
0%
b1 q
b1 p
b10 o
b0 s
1+
#350
0+
#355
b1 w
b10 h
b110 U
b100 '
b100 d
b100 t
1$
1+
#360
0+
#365
b100 '
b100 d
b100 t
1$
1{
b11010001111111010010100000000000 &
b11010001111111010010100000000000 /
b11010001111111010010100000000000 z
b100 b
1+
#370
0+
#375
1%
b100 '
b100 d
b100 t
1$
1+
#380
0+
#385
00
17
b11 h
b10100000000000 -
b10100000000000 S
b100 '
b100 d
b100 t
1$
1+
#390
0+
#395
b0 w
b100 h
b0 \
b10 g
b0 '
b0 d
b0 t
0$
1+
#400
0+
#405
b1 h
0{
0%
b1 q
b0 p
b1 o
1+
#410
0+
#415
b1 w
b10 h
b1000 U
b110 '
b110 d
b110 t
1$
1+
#420
0+
#425
b110 '
b110 d
b110 t
1$
1{
b110 b
1+
#430
0+
#435
1%
b110 '
b110 d
b110 t
1$
1+
#440
0+
#445
1.
07
b11 h
b1101000111111101 -
b1101000111111101 S
b110 '
b110 d
b110 t
1$
1+
#450
0+
#455
b0 w
b100 h
b11111101 \
b1011 g
b0 '
b0 d
b0 t
0$
1+
#460
0+
#465
b1 h
b10 U
0{
0%
b11111111111111111111111111111010 s
b0 q
b0 o
1+
#470
0+
#475
b10 h
b100 U
b10 '
b10 d
b10 t
1$
1+
#480
0+
#485
b10 '
b10 d
b10 t
1$
1{
b111000000000010010000000000011 &
b111000000000010010000000000011 /
b111000000000010010000000000011 z
b10 b
1+
#490
0+
#495
1%
b10 '
b10 d
b10 t
1$
1+
#500
0+
#505
0.
10
b11 h
b11100000000001 -
b11100000000001 S
b10 '
b10 d
b10 t
1$
1+
#510
0+
#515
b100 h
b1 \
b100 g
b0 '
b0 d
b0 t
0$
1+
#520
0+
#525
b1 h
1W
0{
0%
b1 p
b1 o
b0 s
1+
#530
0+
#535
b1 w
b10 h
b110 U
b100 '
b100 d
b100 t
1$
1+
#540
0+
#545
b100 '
b100 d
b100 t
1$
1{
b11010001111111010010100000000000 &
b11010001111111010010100000000000 /
b11010001111111010010100000000000 z
b100 b
1+
#550
0+
#555
1%
b100 '
b100 d
b100 t
1$
1+
#560
0+
#565
00
17
b11 h
b10100000000000 -
b10100000000000 S
b100 '
b100 d
b100 t
1$
1+
#570
0+
#575
b0 w
b100 h
b0 \
b10 g
b0 '
b0 d
b0 t
0$
1+
#580
0+
#585
b1 h
0{
0%
b0 p
b0 o
1+
#590
0+
#595
b1 w
b10 h
b1000 U
b110 '
b110 d
b110 t
1$
1+
#600
0+
#605
b110 '
b110 d
b110 t
1$
1{
b110 b
1+
#610
0+
#615
1%
b110 '
b110 d
b110 t
1$
1+
#620
0+
#625
1.
07
b11 h
b1101000111111101 -
b1101000111111101 S
b110 '
b110 d
b110 t
1$
1+
#630
0+
#635
b0 w
b100 h
b11111101 \
b1011 g
b0 '
b0 d
b0 t
0$
1+
#640
0+
#645
b1 h
0{
0%
b11111111111111111111111111111010 s
1+
#650
0+
#655
b10 w
b10 h
b1010 U
b1000 '
b1000 d
b1000 t
1$
1+
#660
0+
#665
b1000 '
b1000 d
b1000 t
1$
1{
b100001000000010010000010100001 &
b100001000000010010000010100001 /
b100001000000010010000010100001 z
b1000 b
1+
#670
0+
#675
1%
b1000 '
b1000 d
b1000 t
1$
1+
#680
0+
#685
0.
12
b11 h
b10000010100001 -
b10000010100001 S
b1000 '
b1000 d
b1000 t
1$
1+
#690
0+
#695
b0 w
b100 h
b10100001 \
b1 g
b0 '
b0 d
b0 t
0$
1+
#700
0+
